fastapi_ai_sdk/__init__.py
fastapi_ai_sdk/decorators.py
fastapi_ai_sdk/models.py
fastapi_ai_sdk/response.py
fastapi_ai_sdk/stream.py
fastapi_ai_sdk-0.1.0.dist-info/licenses/LICENSE
fastapi_ai_sdk-0.1.0.dist-info/METADATA
fastapi_ai_sdk-0.1.0.dist-info/WHEEL
fastapi_ai_sdk-0.1.0.dist-info/top_level.txt
fastapi_ai_sdk-0.1.0.dist-info/RECORD
