Metadata-Version: 2.4
Name: fastapi-ai-sdk
Version: 0.1.0
Summary: FastAPI helper library for Vercel AI SDK backend implementation
Home-page: https://github.com/doganarif/fastapi-ai-sdk
Author: Arif Dogan
Author-email: Arif Dogan <me@arif.sh>
License: MIT
Project-URL: Homepage, https://github.com/doganarif/fastapi-ai-sdk
Project-URL: Bug Reports, https://github.com/doganarif/fastapi-ai-sdk/issues
Project-URL: Source, https://github.com/doganarif/fastapi-ai-sdk
Project-URL: Documentation, https://github.com/doganarif/fastapi-ai-sdk#readme
Keywords: fastapi,vercel,ai,sdk,streaming,sse,llm
Classifier: Development Status :: 4 - Beta
Classifier: Intended Audience :: Developers
Classifier: License :: OSI Approved :: MIT License
Classifier: Programming Language :: Python :: 3
Classifier: Programming Language :: Python :: 3.9
Classifier: Programming Language :: Python :: 3.10
Classifier: Programming Language :: Python :: 3.11
Classifier: Programming Language :: Python :: 3.12
Classifier: Programming Language :: Python :: 3.13
Classifier: Topic :: Software Development :: Libraries :: Python Modules
Classifier: Topic :: Internet :: WWW/HTTP :: HTTP Servers
Classifier: Framework :: FastAPI
Classifier: Typing :: Typed
Requires-Python: >=3.9
License-File: LICENSE
Requires-Dist: fastapi>=0.115.0
Requires-Dist: pydantic>=2.9.0
Requires-Dist: typing-extensions>=4.12.0
Provides-Extra: dev
Requires-Dist: pytest>=8.3.0; extra == "dev"
Requires-Dist: pytest-asyncio>=0.24.0; extra == "dev"
Requires-Dist: pytest-cov>=5.0.0; extra == "dev"
Requires-Dist: black>=24.10.0; extra == "dev"
Requires-Dist: isort>=5.13.0; extra == "dev"
Requires-Dist: flake8>=7.1.0; extra == "dev"
Requires-Dist: mypy>=1.13.0; extra == "dev"
Requires-Dist: httpx>=0.27.0; extra == "dev"
Requires-Dist: uvicorn>=0.32.0; extra == "dev"
Requires-Dist: ruff>=0.7.0; extra == "dev"
Provides-Extra: examples
Requires-Dist: uvicorn>=0.32.0; extra == "examples"
Requires-Dist: python-multipart>=0.0.12; extra == "examples"
Dynamic: author
Dynamic: home-page
Dynamic: license-file
Dynamic: requires-python
